<?xml version='1.0' encoding='utf-8'?>
<graphml xmlns="http://graphml.graphdrawing.org/xmlns" xmlns:xsi="http://www.w3.org/2001/XMLSchema-instance" xsi:schemaLocation="http://graphml.graphdrawing.org/xmlns http://graphml.graphdrawing.org/xmlns/1.0/graphml.xsd">
  <graph edgedefault="undirected">
    <node id="kirk86" />
    <node id="carlosandrea" />
    <node id="dveni" />
    <node id="puifais" />
    <node id="G-4-R-Y" />
    <node id="LysandreJik" />
    <node id="jordiclive" />
    <node id="seanbenhur" />
    <node id="hyunwoongko" />
    <node id="nadahlberg" />
    <node id="XinhaoMei" />
    <node id="MegaBoboss" />
    <node id="Narsil" />
    <node id="PrithivirajDamodaran" />
    <node id="serdarildercaglar" />
    <node id="alexcoca" />
    <node id="nicholaslike" />
    <node id="Bk073" />
    <node id="arxyzan" />
    <node id="RaiAmanRai" />
    <node id="donaghhorgan" />
    <node id="muellerzr" />
    <node id="fxmarty" />
    <node id="yinzhangyue" />
    <node id="d-miketa" />
    <node id="surya-narayanan" />
    <node id="zhaowei-wang-nlp" />
    <node id="michaelbenayoun" />
    <node id="nreimers" />
    <node id="klyuhang9" />
    <node id="Pzoom522" />
    <node id="ftnext" />
    <node id="taki0112" />
    <node id="woofadu2" />
    <node id="ClonedOne" />
    <node id="catqaq" />
    <node id="Zapotecatl" />
    <node id="bcdarwin" />
    <node id="LSinev" />
    <node id="NielsRogge" />
    <node id="yu-xiang-wang" />
    <node id="marksverdhei" />
    <node id="sanderland" />
    <node id="sgugger" />
    <node id="StefanHeng" />
    <node id="ioana-blue" />
    <node id="patrickvonplaten" />
    <node id="murthyrudra" />
    <node id="srulik-ben-david-hs" />
    <node id="paulthemagno" />
    <node id="SaulLu" />
    <node id="KONAKONA666" />
    <node id="RnoldR" />
    <node id="dinhanhx" />
    <node id="juliensimon" />
    <node id="stas00" />
    <node id="Rababalkhalifa" />
    <node id="mrtoronto" />
    <node id="Abdelrahmanrezk" />
    <node id="nbroad1881" />
    <node id="mygithubid1" />
    <node id="bilalghanem" />
    <node id="JingyaHuang" />
    <node id="gante" />
    <node id="patil-suraj" />
    <node id="chainyo" />
    <node id="miguelwon" />
    <node id="lewtun" />
    <node id="AhmedIdr" />
    <node id="XGZhang11" />
    <node id="elsheikh21" />
    <node id="FrankDataAnalystPython" />
    <node id="ShaneTian" />
    <node id="stancld" />
    <node id="tospirits" />
    <node id="erdoganensar" />
    <node id="ri938" />
    <node id="Sorrow321" />
    <node id="Majdoddin" />
    <node id="sunshineatnoon" />
    <node id="mingxiaoh" />
    <node id="ydshieh" />
    <node id="StephennFernandes" />
    <node id="htthYjh" />
    <node id="Hannibal046" />
    <node id="acadaiaca" />
    <node id="Rocketknight1" />
    <node id="gpucce" />
    <node id="faysalhossain2007" />
    <node id="sanchit-gandhi" />
    <node id="khoda81" />
    <node id="jorgemcgomes" />
    <node id="nkaenzig-aifund" />
    <node id="leo-liuzy" />
    <node id="JoaoLages" />
    <node id="yaozhaogoogle" />
    <node id="IdoAmit198" />
    <node id="10-zin" />
    <node id="changyeli" />
    <node id="craffel" />
    <node id="anderleich" />
    <node id="gugarosa" />
    <node id="hunarbatra" />
    <node id="jieunpark1" />
    <node id="dblakely" />
    <node id="micahcarroll" />
    <node id="kaleko" />
    <node id="wiio12" />
    <node id="KennethEnevoldsen" />
    <node id="TianHongZXY" />
    <node id="JustABiologist" />
    <node id="Oxi84" />
    <node id="sajastu" />
    <node id="Slyne" />
    <node id="ADD-eNavarro" />
    <node id="piEsposito" />
    <node id="gxbag" />
    <node id="HLasse" />
    <node id="slyalin" />
    <node id="deep-mining-swang" />
    <node id="xu1998hz" />
    <node id="beyondguo" />
    <node id="base-y" />
    <node id="Jun-jie-Huang" />
    <node id="omarespejel" />
    <node id="vitorfrois" />
    <node id="lorr1" />
    <node id="thomasw21" />
    <node id="GabrielKP" />
    <node id="CaoYiqingT" />
    <node id="davialvb" />
    <node id="kanwari3" />
    <node id="smitanannaware" />
    <node id="eldarkurtic" />
    <node id="atreyasha" />
    <node id="victorescosta" />
    <node id="rzimmerdev" />
    <node id="Felipehonorato1" />
    <node id="jonatasgrosman" />
    <node id="ajindal1" />
    <node id="Fellip15" />
    <node id="younesbelkada" />
    <node id="osanseviero" />
    <node id="ErinKnochenhauer" />
    <node id="omid0001" />
    <node id="bobbyhaliwela" />
    <node id="fgbelidji" />
    <node id="davidleonfdez" />
    <node id="Charlie-83" />
    <node id="mpoemsl" />
    <node id="AngledLuffa" />
    <node id="jaketae" />
    <node id="gsarti" />
    <node id="Witiko" />
    <node id="bharathc346" />
    <node id="Sandip-Hapani134" />
    <node id="mikcnt" />
    <node id="loretoparisi" />
    <node id="RodSernaPerez" />
    <node id="JessicaLopezEspejel" />
    <node id="Jadiker" />
    <node id="MorenoLaQuatra" />
    <node id="peregilk" />
    <node id="SumanthSrungavarapu" />
    <node id="d-ataman" />
    <node id="PrijsDF" />
    <node id="phayat" />
    <node id="ayaka14732" />
    <node id="JulesGM" />
    <node id="speedcell4" />
    <node id="laurahanu" />
    <node id="gameveloster" />
    <node id="julien-blanchon" />
    <node id="jncasey" />
    <node id="armancohan" />
    <node id="anruijian" />
    <node id="nabarunbaruaAIML" />
    <node id="BramVanroy" />
    <node id="tqnwhz" />
    <node id="NouamaneTazi" />
    <node id="AniketRajpoot" />
    <node id="AbuUbaida" />
    <node id="mareloraby" />
    <node id="CuarteroAlvaro" />
    <node id="emigomez" />
    <node id="YISTANFORD" />
    <node id="RaedShabbir" />
    <node id="edchengg" />
    <node id="julien-c" />
    <node id="jianan-gu" />
    <node id="evros-chris" />
    <node id="i-am-neo" />
    <node id="jgong5" />
    <node id="ZhihaoZhang97" />
    <node id="athewsey" />
    <node id="githublsk" />
    <node id="flozi00" />
    <node id="dboshardy" />
    <node id="yellowjs0304" />
    <node id="TejasDuseja" />
    <node id="tetsu9923" />
    <node id="k-bandi" />
    <node id="SG-Marco" />
    <node id="logan-markewich" />
    <node id="baoyuxu" />
    <node id="ZHM-Sesame" />
    <node id="heyzude" />
    <node id="nihit" />
    <node id="MorningStarOvO" />
    <node id="limapedro" />
    <node id="grassjelly" />
    <node id="KyungHyunLim" />
    <node id="echarlaix" />
    <node id="Zlasejd" />
    <node id="GuillemGSubies" />
    <node id="heraclex12" />
    <node id="zheyuye" />
    <node id="kmehant" />
    <node id="Smu-Tan" />
    <node id="kolk" />
    <node id="pratikchhapolika" />
    <node id="anirudt" />
    <node id="VarunGumma" />
    <node id="02shanks" />
    <node id="leondz" />
    <node id="dmartines" />
    <node id="old-school-kid" />
    <node id="IavTavares" />
    <node id="ierezell" />
    <node id="monsieurpooh" />
    <node id="sijunhe" />
    <node id="srama2512" />
    <node id="maximilianreimer" />
    <node id="GonyRosenman" />
    <node id="antonyscerri" />
    <node id="erip" />
    <node id="deema-A" />
    <node id="warumso7" />
    <node id="yananchen1989" />
    <node id="tahmiddialpad" />
    <node id="code-review-doctor" />
    <node id="chris-opendata" />
    <node id="CaoYiwei" />
    <node id="FrederickXZhang" />
    <node id="maria22431" />
    <node id="nyoungstudios" />
    <node id="stevhliu" />
    <node id="ignacioct" />
    <node id="Pannu22" />
    <node id="wjbmattingly" />
    <node id="FanniSun" />
    <node id="h-peng17" />
    <node id="roywei" />
    <node id="philschmid" />
    <node id="naveace" />
    <node id="ArthurZucker" />
    <node id="Clearloveyuan" />
    <node id="silencio94" />
    <node id="cakiki" />
    <node id="ZhangYunchenY" />
    <node id="markovalexander" />
    <node id="oorojoo" />
    <node id="jtfields" />
    <node id="mingboiz" />
    <node id="ZonglinY" />
    <node id="zhenduow" />
    <node id="JunnYu" />
    <node id="anton-l" />
    <node id="sciai-ai" />
    <node id="cedricrupb" />
    <node id="pepi99" />
    <node id="wlhgtc" />
    <node id="conan1024hao" />
    <node id="qqaatw" />
    <node id="sunhaozhepy" />
    <node id="ksdihgfmata" />
    <node id="realjanpaulus" />
    <node id="StalVars" />
    <node id="YovaKem" />
    <node id="shamanez" />
    <node id="ryanrudes" />
    <node id="orieg" />
    <node id="ElderWanng" />
    <node id="leminhyen2" />
    <node id="dumpmemory" />
    <node id="Nana12345678910" />
    <node id="wolhandlerdeb" />
    <node id="NextNight" />
    <node id="shira-g" />
    <node id="YianZhang" />
    <node id="OfirArviv" />
    <node id="danzz006" />
    <node id="rafikg" />
    <node id="czy-orange" />
    <node id="zhufeijuanjuan" />
    <node id="HuihuiChyan" />
    <node id="bariluz93" />
    <node id="joeyism" />
    <node id="Bachstelze" />
    <node id="stefan-it" />
    <node id="Kyeongpil" />
    <node id="WissamAntoun" />
    <node id="HallerPatrick" />
    <node id="nancy-zhang" />
    <node id="tkella47" />
    <node id="eneko98" />
    <node id="johnnytam100" />
    <node id="maovshao" />
    <edge source="kirk86" target="carlosandrea" />
    <edge source="kirk86" target="dveni" />
    <edge source="kirk86" target="puifais" />
    <edge source="kirk86" target="G-4-R-Y" />
    <edge source="kirk86" target="LysandreJik" />
    <edge source="carlosandrea" target="puifais" />
    <edge source="carlosandrea" target="G-4-R-Y" />
    <edge source="carlosandrea" target="dveni" />
    <edge source="carlosandrea" target="LysandreJik" />
    <edge source="dveni" target="puifais" />
    <edge source="dveni" target="G-4-R-Y" />
    <edge source="dveni" target="LysandreJik" />
    <edge source="puifais" target="G-4-R-Y" />
    <edge source="puifais" target="LysandreJik" />
    <edge source="G-4-R-Y" target="LysandreJik" />
    <edge source="LysandreJik" target="jordiclive" />
    <edge source="LysandreJik" target="seanbenhur" />
    <edge source="LysandreJik" target="hyunwoongko" />
    <edge source="LysandreJik" target="nadahlberg" />
    <edge source="LysandreJik" target="XinhaoMei" />
    <edge source="LysandreJik" target="MegaBoboss" />
    <edge source="LysandreJik" target="Narsil" />
    <edge source="LysandreJik" target="PrithivirajDamodaran" />
    <edge source="LysandreJik" target="serdarildercaglar" />
    <edge source="LysandreJik" target="alexcoca" />
    <edge source="LysandreJik" target="nicholaslike" />
    <edge source="LysandreJik" target="Bk073" />
    <edge source="LysandreJik" target="arxyzan" />
    <edge source="LysandreJik" target="RaiAmanRai" />
    <edge source="LysandreJik" target="donaghhorgan" />
    <edge source="LysandreJik" target="muellerzr" />
    <edge source="LysandreJik" target="fxmarty" />
    <edge source="LysandreJik" target="yinzhangyue" />
    <edge source="LysandreJik" target="d-miketa" />
    <edge source="LysandreJik" target="surya-narayanan" />
    <edge source="LysandreJik" target="zhaowei-wang-nlp" />
    <edge source="LysandreJik" target="michaelbenayoun" />
    <edge source="LysandreJik" target="nreimers" />
    <edge source="LysandreJik" target="klyuhang9" />
    <edge source="LysandreJik" target="Pzoom522" />
    <edge source="LysandreJik" target="ftnext" />
    <edge source="LysandreJik" target="taki0112" />
    <edge source="LysandreJik" target="woofadu2" />
    <edge source="LysandreJik" target="ClonedOne" />
    <edge source="LysandreJik" target="catqaq" />
    <edge source="LysandreJik" target="Zapotecatl" />
    <edge source="LysandreJik" target="bcdarwin" />
    <edge source="LysandreJik" target="LSinev" />
    <edge source="LysandreJik" target="NielsRogge" />
    <edge source="LysandreJik" target="yu-xiang-wang" />
    <edge source="LysandreJik" target="marksverdhei" />
    <edge source="LysandreJik" target="sanderland" />
    <edge source="LysandreJik" target="sgugger" />
    <edge source="LysandreJik" target="StefanHeng" />
    <edge source="LysandreJik" target="ioana-blue" />
    <edge source="LysandreJik" target="patrickvonplaten" />
    <edge source="LysandreJik" target="murthyrudra" />
    <edge source="LysandreJik" target="srulik-ben-david-hs" />
    <edge source="LysandreJik" target="paulthemagno" />
    <edge source="LysandreJik" target="SaulLu" />
    <edge source="LysandreJik" target="KONAKONA666" />
    <edge source="LysandreJik" target="RnoldR" />
    <edge source="LysandreJik" target="dinhanhx" />
    <edge source="LysandreJik" target="juliensimon" />
    <edge source="LysandreJik" target="stas00" />
    <edge source="LysandreJik" target="Rababalkhalifa" />
    <edge source="LysandreJik" target="mrtoronto" />
    <edge source="LysandreJik" target="Abdelrahmanrezk" />
    <edge source="LysandreJik" target="nbroad1881" />
    <edge source="LysandreJik" target="mygithubid1" />
    <edge source="LysandreJik" target="bilalghanem" />
    <edge source="LysandreJik" target="JingyaHuang" />
    <edge source="LysandreJik" target="gante" />
    <edge source="LysandreJik" target="patil-suraj" />
    <edge source="LysandreJik" target="chainyo" />
    <edge source="LysandreJik" target="miguelwon" />
    <edge source="LysandreJik" target="lewtun" />
    <edge source="LysandreJik" target="AhmedIdr" />
    <edge source="jordiclive" target="michaelbenayoun" />
    <edge source="jordiclive" target="lewtun" />
    <edge source="jordiclive" target="nadahlberg" />
    <edge source="jordiclive" target="JingyaHuang" />
    <edge source="seanbenhur" target="NielsRogge" />
    <edge source="hyunwoongko" target="Abdelrahmanrezk" />
    <edge source="hyunwoongko" target="taki0112" />
    <edge source="nadahlberg" target="michaelbenayoun" />
    <edge source="nadahlberg" target="lewtun" />
    <edge source="nadahlberg" target="JingyaHuang" />
    <edge source="XinhaoMei" target="patrickvonplaten" />
    <edge source="XinhaoMei" target="Bk073" />
    <edge source="Narsil" target="patrickvonplaten" />
    <edge source="Narsil" target="sgugger" />
    <edge source="Narsil" target="SaulLu" />
    <edge source="Narsil" target="Rocketknight1" />
    <edge source="Narsil" target="dmartines" />
    <edge source="Narsil" target="FrankDataAnalystPython" />
    <edge source="Narsil" target="ierezell" />
    <edge source="Narsil" target="fxmarty" />
    <edge source="Narsil" target="Witiko" />
    <edge source="Narsil" target="monsieurpooh" />
    <edge source="Narsil" target="sijunhe" />
    <edge source="Narsil" target="srama2512" />
    <edge source="Narsil" target="maximilianreimer" />
    <edge source="Narsil" target="GonyRosenman" />
    <edge source="Narsil" target="antonyscerri" />
    <edge source="Narsil" target="erip" />
    <edge source="Narsil" target="IavTavares" />
    <edge source="Narsil" target="fgbelidji" />
    <edge source="PrithivirajDamodaran" target="NielsRogge" />
    <edge source="PrithivirajDamodaran" target="k-bandi" />
    <edge source="PrithivirajDamodaran" target="nihit" />
    <edge source="serdarildercaglar" target="michaelbenayoun" />
    <edge source="serdarildercaglar" target="lewtun" />
    <edge source="serdarildercaglar" target="RaiAmanRai" />
    <edge source="alexcoca" target="sgugger" />
    <edge source="alexcoca" target="stas00" />
    <edge source="alexcoca" target="julien-c" />
    <edge source="alexcoca" target="edchengg" />
    <edge source="alexcoca" target="i-am-neo" />
    <edge source="nicholaslike" target="marksverdhei" />
    <edge source="nicholaslike" target="miguelwon" />
    <edge source="nicholaslike" target="muellerzr" />
    <edge source="Bk073" target="patrickvonplaten" />
    <edge source="arxyzan" target="NielsRogge" />
    <edge source="RaiAmanRai" target="michaelbenayoun" />
    <edge source="RaiAmanRai" target="lewtun" />
    <edge source="donaghhorgan" target="nbroad1881" />
    <edge source="donaghhorgan" target="bcdarwin" />
    <edge source="donaghhorgan" target="yu-xiang-wang" />
    <edge source="donaghhorgan" target="ioana-blue" />
    <edge source="donaghhorgan" target="woofadu2" />
    <edge source="muellerzr" target="marksverdhei" />
    <edge source="muellerzr" target="miguelwon" />
    <edge source="d-miketa" target="Zlasejd" />
    <edge source="d-miketa" target="GuillemGSubies" />
    <edge source="surya-narayanan" target="sgugger" />
    <edge source="surya-narayanan" target="nreimers" />
    <edge source="zhaowei-wang-nlp" target="sgugger" />
    <edge source="zhaowei-wang-nlp" target="stas00" />
    <edge source="michaelbenayoun" target="XGZhang11" />
    <edge source="michaelbenayoun" target="lewtun" />
    <edge source="michaelbenayoun" target="JingyaHuang" />
    <edge source="nreimers" target="sgugger" />
    <edge source="ftnext" target="sgugger" />
    <edge source="ftnext" target="stevhliu" />
    <edge source="taki0112" target="Abdelrahmanrezk" />
    <edge source="woofadu2" target="nbroad1881" />
    <edge source="woofadu2" target="bcdarwin" />
    <edge source="woofadu2" target="ioana-blue" />
    <edge source="woofadu2" target="yu-xiang-wang" />
    <edge source="ClonedOne" target="sgugger" />
    <edge source="catqaq" target="gante" />
    <edge source="Zapotecatl" target="chainyo" />
    <edge source="Zapotecatl" target="KONAKONA666" />
    <edge source="bcdarwin" target="nbroad1881" />
    <edge source="bcdarwin" target="yu-xiang-wang" />
    <edge source="bcdarwin" target="ioana-blue" />
    <edge source="LSinev" target="sgugger" />
    <edge source="NielsRogge" target="patrickvonplaten" />
    <edge source="NielsRogge" target="ZhihaoZhang97" />
    <edge source="NielsRogge" target="athewsey" />
    <edge source="NielsRogge" target="githublsk" />
    <edge source="NielsRogge" target="flozi00" />
    <edge source="NielsRogge" target="dboshardy" />
    <edge source="NielsRogge" target="yellowjs0304" />
    <edge source="NielsRogge" target="TejasDuseja" />
    <edge source="NielsRogge" target="tetsu9923" />
    <edge source="NielsRogge" target="srulik-ben-david-hs" />
    <edge source="NielsRogge" target="k-bandi" />
    <edge source="NielsRogge" target="SG-Marco" />
    <edge source="NielsRogge" target="Sorrow321" />
    <edge source="NielsRogge" target="logan-markewich" />
    <edge source="NielsRogge" target="baoyuxu" />
    <edge source="NielsRogge" target="ZHM-Sesame" />
    <edge source="NielsRogge" target="heyzude" />
    <edge source="NielsRogge" target="nihit" />
    <edge source="NielsRogge" target="MorningStarOvO" />
    <edge source="NielsRogge" target="limapedro" />
    <edge source="NielsRogge" target="grassjelly" />
    <edge source="yu-xiang-wang" target="nbroad1881" />
    <edge source="yu-xiang-wang" target="ioana-blue" />
    <edge source="marksverdhei" target="patrickvonplaten" />
    <edge source="marksverdhei" target="Majdoddin" />
    <edge source="marksverdhei" target="miguelwon" />
    <edge source="sgugger" target="patrickvonplaten" />
    <edge source="sgugger" target="gpucce" />
    <edge source="sgugger" target="beyondguo" />
    <edge source="sgugger" target="base-y" />
    <edge source="sgugger" target="Jun-jie-Huang" />
    <edge source="sgugger" target="omarespejel" />
    <edge source="sgugger" target="vitorfrois" />
    <edge source="sgugger" target="lorr1" />
    <edge source="sgugger" target="thomasw21" />
    <edge source="sgugger" target="tospirits" />
    <edge source="sgugger" target="GabrielKP" />
    <edge source="sgugger" target="mingxiaoh" />
    <edge source="sgugger" target="ydshieh" />
    <edge source="sgugger" target="StephennFernandes" />
    <edge source="sgugger" target="acadaiaca" />
    <edge source="sgugger" target="CaoYiqingT" />
    <edge source="sgugger" target="davialvb" />
    <edge source="sgugger" target="kanwari3" />
    <edge source="sgugger" target="smitanannaware" />
    <edge source="sgugger" target="eldarkurtic" />
    <edge source="sgugger" target="atreyasha" />
    <edge source="sgugger" target="victorescosta" />
    <edge source="sgugger" target="rzimmerdev" />
    <edge source="sgugger" target="Felipehonorato1" />
    <edge source="sgugger" target="jonatasgrosman" />
    <edge source="sgugger" target="IdoAmit198" />
    <edge source="sgugger" target="10-zin" />
    <edge source="sgugger" target="gugarosa" />
    <edge source="sgugger" target="ajindal1" />
    <edge source="sgugger" target="murthyrudra" />
    <edge source="sgugger" target="Fellip15" />
    <edge source="sgugger" target="younesbelkada" />
    <edge source="sgugger" target="stas00" />
    <edge source="sgugger" target="nbroad1881" />
    <edge source="sgugger" target="sajastu" />
    <edge source="sgugger" target="Slyne" />
    <edge source="sgugger" target="osanseviero" />
    <edge source="sgugger" target="patil-suraj" />
    <edge source="sgugger" target="ErinKnochenhauer" />
    <edge source="sgugger" target="omid0001" />
    <edge source="sgugger" target="bobbyhaliwela" />
    <edge source="sgugger" target="fgbelidji" />
    <edge source="ioana-blue" target="nbroad1881" />
    <edge source="patrickvonplaten" target="elsheikh21" />
    <edge source="patrickvonplaten" target="FrankDataAnalystPython" />
    <edge source="patrickvonplaten" target="ShaneTian" />
    <edge source="patrickvonplaten" target="stancld" />
    <edge source="patrickvonplaten" target="tospirits" />
    <edge source="patrickvonplaten" target="erdoganensar" />
    <edge source="patrickvonplaten" target="ri938" />
    <edge source="patrickvonplaten" target="Sorrow321" />
    <edge source="patrickvonplaten" target="Majdoddin" />
    <edge source="patrickvonplaten" target="sunshineatnoon" />
    <edge source="patrickvonplaten" target="mingxiaoh" />
    <edge source="patrickvonplaten" target="ydshieh" />
    <edge source="patrickvonplaten" target="StephennFernandes" />
    <edge source="patrickvonplaten" target="htthYjh" />
    <edge source="patrickvonplaten" target="Hannibal046" />
    <edge source="patrickvonplaten" target="acadaiaca" />
    <edge source="patrickvonplaten" target="Rocketknight1" />
    <edge source="patrickvonplaten" target="gpucce" />
    <edge source="patrickvonplaten" target="faysalhossain2007" />
    <edge source="patrickvonplaten" target="sanchit-gandhi" />
    <edge source="patrickvonplaten" target="khoda81" />
    <edge source="patrickvonplaten" target="jorgemcgomes" />
    <edge source="patrickvonplaten" target="nkaenzig-aifund" />
    <edge source="patrickvonplaten" target="leo-liuzy" />
    <edge source="patrickvonplaten" target="JoaoLages" />
    <edge source="patrickvonplaten" target="yaozhaogoogle" />
    <edge source="patrickvonplaten" target="IdoAmit198" />
    <edge source="patrickvonplaten" target="10-zin" />
    <edge source="patrickvonplaten" target="changyeli" />
    <edge source="patrickvonplaten" target="craffel" />
    <edge source="patrickvonplaten" target="anderleich" />
    <edge source="patrickvonplaten" target="gugarosa" />
    <edge source="patrickvonplaten" target="hunarbatra" />
    <edge source="patrickvonplaten" target="jieunpark1" />
    <edge source="patrickvonplaten" target="dblakely" />
    <edge source="patrickvonplaten" target="paulthemagno" />
    <edge source="patrickvonplaten" target="micahcarroll" />
    <edge source="patrickvonplaten" target="SaulLu" />
    <edge source="patrickvonplaten" target="kaleko" />
    <edge source="patrickvonplaten" target="wiio12" />
    <edge source="patrickvonplaten" target="KennethEnevoldsen" />
    <edge source="patrickvonplaten" target="TianHongZXY" />
    <edge source="patrickvonplaten" target="JustABiologist" />
    <edge source="patrickvonplaten" target="Oxi84" />
    <edge source="patrickvonplaten" target="sajastu" />
    <edge source="patrickvonplaten" target="Slyne" />
    <edge source="patrickvonplaten" target="ADD-eNavarro" />
    <edge source="patrickvonplaten" target="gante" />
    <edge source="patrickvonplaten" target="patil-suraj" />
    <edge source="patrickvonplaten" target="piEsposito" />
    <edge source="patrickvonplaten" target="gxbag" />
    <edge source="patrickvonplaten" target="HLasse" />
    <edge source="patrickvonplaten" target="slyalin" />
    <edge source="patrickvonplaten" target="deep-mining-swang" />
    <edge source="patrickvonplaten" target="xu1998hz" />
    <edge source="paulthemagno" target="patil-suraj" />
    <edge source="SaulLu" target="davidleonfdez" />
    <edge source="SaulLu" target="Charlie-83" />
    <edge source="SaulLu" target="Oxi84" />
    <edge source="SaulLu" target="mpoemsl" />
    <edge source="SaulLu" target="AngledLuffa" />
    <edge source="SaulLu" target="jaketae" />
    <edge source="SaulLu" target="gsarti" />
    <edge source="SaulLu" target="Witiko" />
    <edge source="SaulLu" target="bharathc346" />
    <edge source="KONAKONA666" target="chainyo" />
    <edge source="stas00" target="jaketae" />
    <edge source="stas00" target="edchengg" />
    <edge source="stas00" target="base-y" />
    <edge source="stas00" target="julien-blanchon" />
    <edge source="stas00" target="julien-c" />
    <edge source="stas00" target="jianan-gu" />
    <edge source="stas00" target="evros-chris" />
    <edge source="stas00" target="jncasey" />
    <edge source="stas00" target="osanseviero" />
    <edge source="stas00" target="gameveloster" />
    <edge source="stas00" target="i-am-neo" />
    <edge source="stas00" target="smitanannaware" />
    <edge source="stas00" target="jgong5" />
    <edge source="JingyaHuang" target="lewtun" />
    <edge source="gante" target="JoaoLages" />
    <edge source="gante" target="Sandip-Hapani134" />
    <edge source="gante" target="mikcnt" />
    <edge source="gante" target="ydshieh" />
    <edge source="gante" target="loretoparisi" />
    <edge source="gante" target="TianHongZXY" />
    <edge source="gante" target="RodSernaPerez" />
    <edge source="gante" target="JessicaLopezEspejel" />
    <edge source="gante" target="Rocketknight1" />
    <edge source="gante" target="patil-suraj" />
    <edge source="gante" target="piEsposito" />
    <edge source="gante" target="Jadiker" />
    <edge source="gante" target="sanchit-gandhi" />
    <edge source="gante" target="dblakely" />
    <edge source="gante" target="slyalin" />
    <edge source="patil-suraj" target="MorenoLaQuatra" />
    <edge source="patil-suraj" target="stancld" />
    <edge source="patil-suraj" target="tospirits" />
    <edge source="patil-suraj" target="ri938" />
    <edge source="patil-suraj" target="mingxiaoh" />
    <edge source="patil-suraj" target="StephennFernandes" />
    <edge source="patil-suraj" target="peregilk" />
    <edge source="patil-suraj" target="htthYjh" />
    <edge source="patil-suraj" target="SumanthSrungavarapu" />
    <edge source="patil-suraj" target="d-ataman" />
    <edge source="patil-suraj" target="acadaiaca" />
    <edge source="patil-suraj" target="Rocketknight1" />
    <edge source="patil-suraj" target="sanchit-gandhi" />
    <edge source="patil-suraj" target="PrijsDF" />
    <edge source="patil-suraj" target="jorgemcgomes" />
    <edge source="patil-suraj" target="phayat" />
    <edge source="patil-suraj" target="IdoAmit198" />
    <edge source="patil-suraj" target="ayaka14732" />
    <edge source="patil-suraj" target="10-zin" />
    <edge source="patil-suraj" target="JulesGM" />
    <edge source="patil-suraj" target="craffel" />
    <edge source="patil-suraj" target="anderleich" />
    <edge source="patil-suraj" target="gugarosa" />
    <edge source="patil-suraj" target="speedcell4" />
    <edge source="patil-suraj" target="hunarbatra" />
    <edge source="patil-suraj" target="dblakely" />
    <edge source="patil-suraj" target="kaleko" />
    <edge source="patil-suraj" target="KennethEnevoldsen" />
    <edge source="patil-suraj" target="TianHongZXY" />
    <edge source="patil-suraj" target="JustABiologist" />
    <edge source="patil-suraj" target="sajastu" />
    <edge source="patil-suraj" target="gxbag" />
    <edge source="patil-suraj" target="HLasse" />
    <edge source="patil-suraj" target="slyalin" />
    <edge source="patil-suraj" target="deep-mining-swang" />
    <edge source="chainyo" target="nyoungstudios" />
    <edge source="lewtun" target="echarlaix" />
    <edge source="elsheikh21" target="ADD-eNavarro" />
    <edge source="tospirits" target="sajastu" />
    <edge source="tospirits" target="gugarosa" />
    <edge source="tospirits" target="mingxiaoh" />
    <edge source="tospirits" target="StephennFernandes" />
    <edge source="tospirits" target="10-zin" />
    <edge source="tospirits" target="IdoAmit198" />
    <edge source="tospirits" target="acadaiaca" />
    <edge source="erdoganensar" target="changyeli" />
    <edge source="ri938" target="htthYjh" />
    <edge source="sunshineatnoon" target="faysalhossain2007" />
    <edge source="mingxiaoh" target="sajastu" />
    <edge source="mingxiaoh" target="gugarosa" />
    <edge source="mingxiaoh" target="StephennFernandes" />
    <edge source="mingxiaoh" target="IdoAmit198" />
    <edge source="mingxiaoh" target="10-zin" />
    <edge source="mingxiaoh" target="acadaiaca" />
    <edge source="ydshieh" target="tqnwhz" />
    <edge source="ydshieh" target="NouamaneTazi" />
    <edge source="ydshieh" target="AniketRajpoot" />
    <edge source="ydshieh" target="AbuUbaida" />
    <edge source="ydshieh" target="mareloraby" />
    <edge source="ydshieh" target="Rocketknight1" />
    <edge source="ydshieh" target="CuarteroAlvaro" />
    <edge source="ydshieh" target="emigomez" />
    <edge source="ydshieh" target="sanchit-gandhi" />
    <edge source="ydshieh" target="kanwari3" />
    <edge source="ydshieh" target="YISTANFORD" />
    <edge source="ydshieh" target="RaedShabbir" />
    <edge source="ydshieh" target="omid0001" />
    <edge source="ydshieh" target="micahcarroll" />
    <edge source="StephennFernandes" target="sajastu" />
    <edge source="StephennFernandes" target="gugarosa" />
    <edge source="StephennFernandes" target="IdoAmit198" />
    <edge source="StephennFernandes" target="10-zin" />
    <edge source="StephennFernandes" target="acadaiaca" />
    <edge source="acadaiaca" target="sajastu" />
    <edge source="acadaiaca" target="gugarosa" />
    <edge source="acadaiaca" target="10-zin" />
    <edge source="acadaiaca" target="IdoAmit198" />
    <edge source="Rocketknight1" target="sanchit-gandhi" />
    <edge source="Rocketknight1" target="craffel" />
    <edge source="Rocketknight1" target="jorgemcgomes" />
    <edge source="Rocketknight1" target="dmartines" />
    <edge source="Rocketknight1" target="old-school-kid" />
    <edge source="Rocketknight1" target="IavTavares" />
    <edge source="Rocketknight1" target="RodSernaPerez" />
    <edge source="jorgemcgomes" target="craffel" />
    <edge source="IdoAmit198" target="sajastu" />
    <edge source="IdoAmit198" target="gugarosa" />
    <edge source="IdoAmit198" target="10-zin" />
    <edge source="10-zin" target="sajastu" />
    <edge source="10-zin" target="gugarosa" />
    <edge source="anderleich" target="kaleko" />
    <edge source="anderleich" target="gxbag" />
    <edge source="gugarosa" target="sajastu" />
    <edge source="hunarbatra" target="deep-mining-swang" />
    <edge source="hunarbatra" target="JustABiologist" />
    <edge source="jieunpark1" target="HLasse" />
    <edge source="dblakely" target="TianHongZXY" />
    <edge source="dblakely" target="slyalin" />
    <edge source="kaleko" target="gxbag" />
    <edge source="KennethEnevoldsen" target="HLasse" />
    <edge source="TianHongZXY" target="slyalin" />
    <edge source="JustABiologist" target="deep-mining-swang" />
    <edge source="Oxi84" target="jaketae" />
    <edge source="Oxi84" target="GabrielKP" />
    <edge source="Oxi84" target="armancohan" />
    <edge source="Oxi84" target="anruijian" />
    <edge source="sajastu" target="chris-opendata" />
    <edge source="base-y" target="smitanannaware" />
    <edge source="Jun-jie-Huang" target="CaoYiqingT" />
    <edge source="omarespejel" target="stevhliu" />
    <edge source="omarespejel" target="ignacioct" />
    <edge source="omarespejel" target="vitorfrois" />
    <edge source="omarespejel" target="osanseviero" />
    <edge source="omarespejel" target="jonatasgrosman" />
    <edge source="omarespejel" target="davialvb" />
    <edge source="omarespejel" target="victorescosta" />
    <edge source="omarespejel" target="rzimmerdev" />
    <edge source="omarespejel" target="Felipehonorato1" />
    <edge source="omarespejel" target="Fellip15" />
    <edge source="vitorfrois" target="jonatasgrosman" />
    <edge source="vitorfrois" target="osanseviero" />
    <edge source="vitorfrois" target="davialvb" />
    <edge source="vitorfrois" target="rzimmerdev" />
    <edge source="vitorfrois" target="Fellip15" />
    <edge source="vitorfrois" target="victorescosta" />
    <edge source="vitorfrois" target="Felipehonorato1" />
    <edge source="thomasw21" target="younesbelkada" />
    <edge source="GabrielKP" target="armancohan" />
    <edge source="GabrielKP" target="anruijian" />
    <edge source="davialvb" target="jonatasgrosman" />
    <edge source="davialvb" target="osanseviero" />
    <edge source="davialvb" target="Fellip15" />
    <edge source="davialvb" target="victorescosta" />
    <edge source="davialvb" target="rzimmerdev" />
    <edge source="davialvb" target="Felipehonorato1" />
    <edge source="kanwari3" target="omid0001" />
    <edge source="victorescosta" target="jonatasgrosman" />
    <edge source="victorescosta" target="osanseviero" />
    <edge source="victorescosta" target="rzimmerdev" />
    <edge source="victorescosta" target="Felipehonorato1" />
    <edge source="victorescosta" target="Fellip15" />
    <edge source="rzimmerdev" target="jonatasgrosman" />
    <edge source="rzimmerdev" target="osanseviero" />
    <edge source="rzimmerdev" target="Fellip15" />
    <edge source="rzimmerdev" target="Felipehonorato1" />
    <edge source="Felipehonorato1" target="jonatasgrosman" />
    <edge source="Felipehonorato1" target="osanseviero" />
    <edge source="Felipehonorato1" target="Fellip15" />
    <edge source="jonatasgrosman" target="Fellip15" />
    <edge source="jonatasgrosman" target="osanseviero" />
    <edge source="Fellip15" target="osanseviero" />
    <edge source="jaketae" target="gameveloster" />
    <edge source="jaketae" target="julien-blanchon" />
    <edge source="jaketae" target="jncasey" />
    <edge source="mikcnt" target="JessicaLopezEspejel" />
    <edge source="peregilk" target="d-ataman" />
    <edge source="SumanthSrungavarapu" target="phayat" />
    <edge source="gameveloster" target="julien-blanchon" />
    <edge source="gameveloster" target="jncasey" />
    <edge source="julien-blanchon" target="jncasey" />
    <edge source="armancohan" target="anruijian" />
    <edge source="tqnwhz" target="AbuUbaida" />
    <edge source="tqnwhz" target="AniketRajpoot" />
    <edge source="tqnwhz" target="mareloraby" />
    <edge source="NouamaneTazi" target="CuarteroAlvaro" />
    <edge source="NouamaneTazi" target="emigomez" />
    <edge source="AniketRajpoot" target="RaedShabbir" />
    <edge source="AniketRajpoot" target="AbuUbaida" />
    <edge source="AniketRajpoot" target="mareloraby" />
    <edge source="AbuUbaida" target="RaedShabbir" />
    <edge source="AbuUbaida" target="mareloraby" />
    <edge source="CuarteroAlvaro" target="emigomez" />
    <edge source="YISTANFORD" target="RaedShabbir" />
    <edge source="RaedShabbir" target="zhufeijuanjuan" />
    <edge source="edchengg" target="julien-c" />
    <edge source="edchengg" target="i-am-neo" />
    <edge source="julien-c" target="i-am-neo" />
    <edge source="jianan-gu" target="jgong5" />
    <edge source="githublsk" target="logan-markewich" />
    <edge source="flozi00" target="limapedro" />
    <edge source="dboshardy" target="heyzude" />
    <edge source="k-bandi" target="nihit" />
    <edge source="SG-Marco" target="grassjelly" />
    <edge source="Zlasejd" target="GuillemGSubies" />
    <edge source="heraclex12" target="zheyuye" />
    <edge source="kmehant" target="Smu-Tan" />
    <edge source="anirudt" target="VarunGumma" />
    <edge source="anirudt" target="02shanks" />
    <edge source="VarunGumma" target="02shanks" />
    <edge source="02shanks" target="leondz" />
    <edge source="dmartines" target="IavTavares" />
    <edge source="monsieurpooh" target="srama2512" />
    <edge source="monsieurpooh" target="GonyRosenman" />
    <edge source="sijunhe" target="maximilianreimer" />
    <edge source="sijunhe" target="ZonglinY" />
    <edge source="sijunhe" target="zhenduow" />
    <edge source="srama2512" target="GonyRosenman" />
    <edge source="deema-A" target="warumso7" />
    <edge source="yananchen1989" target="tahmiddialpad" />
    <edge source="stevhliu" target="ignacioct" />
    <edge source="Pannu22" target="wjbmattingly" />
    <edge source="roywei" target="philschmid" />
    <edge source="jtfields" target="mingboiz" />
    <edge source="ZonglinY" target="zhenduow" />
    <edge source="anton-l" target="sciai-ai" />
    <edge source="wlhgtc" target="conan1024hao" />
    <edge source="StalVars" target="YovaKem" />
    <edge source="StalVars" target="shamanez" />
    <edge source="YovaKem" target="shamanez" />
    <edge source="ElderWanng" target="leminhyen2" />
    <edge source="ElderWanng" target="dumpmemory" />
    <edge source="ElderWanng" target="Nana12345678910" />
    <edge source="leminhyen2" target="dumpmemory" />
    <edge source="leminhyen2" target="Nana12345678910" />
    <edge source="dumpmemory" target="Nana12345678910" />
    <edge source="NextNight" target="shira-g" />
    <edge source="NextNight" target="YianZhang" />
    <edge source="NextNight" target="OfirArviv" />
    <edge source="NextNight" target="danzz006" />
    <edge source="shira-g" target="OfirArviv" />
    <edge source="shira-g" target="YianZhang" />
    <edge source="shira-g" target="danzz006" />
    <edge source="YianZhang" target="OfirArviv" />
    <edge source="YianZhang" target="danzz006" />
    <edge source="OfirArviv" target="danzz006" />
    <edge source="rafikg" target="czy-orange" />
    <edge source="Bachstelze" target="stefan-it" />
    <edge source="Kyeongpil" target="WissamAntoun" />
    <edge source="nancy-zhang" target="tkella47" />
    <edge source="nancy-zhang" target="eneko98" />
    <edge source="nancy-zhang" target="johnnytam100" />
    <edge source="nancy-zhang" target="maovshao" />
    <edge source="tkella47" target="eneko98" />
    <edge source="tkella47" target="maovshao" />
    <edge source="tkella47" target="johnnytam100" />
    <edge source="eneko98" target="johnnytam100" />
    <edge source="eneko98" target="maovshao" />
    <edge source="johnnytam100" target="maovshao" />
  </graph>
</graphml>
