<?xml version='1.0' encoding='utf-8'?>
<graphml xmlns="http://graphml.graphdrawing.org/xmlns" xmlns:xsi="http://www.w3.org/2001/XMLSchema-instance" xsi:schemaLocation="http://graphml.graphdrawing.org/xmlns http://graphml.graphdrawing.org/xmlns/1.0/graphml.xsd">
  <graph edgedefault="undirected">
    <node id="iigorkarpov" />
    <node id="solracsf" />
    <node id="jarmo" />
    <node id="cvalentine99" />
    <node id="SteveBox0" />
    <node id="cpipilas" />
    <node id="ghuntley" />
    <node id="ewlikodjo" />
    <node id="ilyam8" />
    <node id="netdata-community-bot" />
    <node id="tomeq82" />
    <node id="ValorousSalmon" />
    <node id="Ferroin" />
    <node id="ktsaou" />
    <node id="PatTheMav" />
    <node id="tkatsoulas" />
    <node id="vlvkobal" />
    <node id="maneamarius" />
    <node id="Piroro-hs" />
    <node id="renantea" />
    <node id="IslamAlam" />
    <node id="solution-al" />
    <node id="mikehearn" />
    <node id="stelfrag" />
    <node id="thunko" />
    <node id="surajnpn" />
    <node id="MatthewABrantley" />
    <node id="hx210" />
    <node id="IDeletedSystem64" />
    <node id="hugovalente-pm" />
    <node id="MrZammler" />
    <node id="DmitruMoth" />
    <node id="Famku" />
    <node id="lzclff" />
    <node id="andrewm4894" />
    <node id="k0ste" />
    <node id="drawks" />
    <node id="thiagoftsm" />
    <node id="diizzyy" />
    <node id="superusercode" />
    <node id="gmta" />
    <node id="jinetjose" />
    <node id="odidev" />
    <node id="callumgare" />
    <node id="underhood" />
    <node id="ghoekstra" />
    <node id="ralphm" />
    <node id="kryztoval" />
    <node id="jrca025" />
    <node id="RubenKelevra" />
    <node id="PanosJee" />
    <node id="cakrit" />
    <node id="crafty35a" />
    <node id="realEthanZou" />
    <node id="luison" />
    <node id="anilskalyane" />
    <node id="gary-albano" />
    <node id="William8Work" />
    <node id="vickyingle01" />
    <node id="vkuznecovas" />
    <node id="timowevel1" />
    <node id="xyzulu" />
    <node id="Anasxrt" />
    <node id="iredmail" />
    <node id="dragon2611" />
    <node id="odynik" />
    <node id="shyamvalsan" />
    <node id="vkalintiris" />
    <node id="webdock-io" />
    <edge source="iigorkarpov" target="solracsf" />
    <edge source="iigorkarpov" target="jarmo" />
    <edge source="iigorkarpov" target="cvalentine99" />
    <edge source="iigorkarpov" target="SteveBox0" />
    <edge source="iigorkarpov" target="cpipilas" />
    <edge source="iigorkarpov" target="ghuntley" />
    <edge source="iigorkarpov" target="ewlikodjo" />
    <edge source="iigorkarpov" target="ilyam8" />
    <edge source="iigorkarpov" target="netdata-community-bot" />
    <edge source="iigorkarpov" target="tomeq82" />
    <edge source="iigorkarpov" target="ValorousSalmon" />
    <edge source="iigorkarpov" target="Ferroin" />
    <edge source="iigorkarpov" target="ktsaou" />
    <edge source="iigorkarpov" target="PatTheMav" />
    <edge source="iigorkarpov" target="tkatsoulas" />
    <edge source="iigorkarpov" target="vlvkobal" />
    <edge source="iigorkarpov" target="maneamarius" />
    <edge source="iigorkarpov" target="Piroro-hs" />
    <edge source="iigorkarpov" target="renantea" />
    <edge source="iigorkarpov" target="IslamAlam" />
    <edge source="iigorkarpov" target="solution-al" />
    <edge source="iigorkarpov" target="mikehearn" />
    <edge source="iigorkarpov" target="stelfrag" />
    <edge source="solracsf" target="ilyam8" />
    <edge source="solracsf" target="Ferroin" />
    <edge source="solracsf" target="mikehearn" />
    <edge source="solracsf" target="PatTheMav" />
    <edge source="solracsf" target="surajnpn" />
    <edge source="solracsf" target="maneamarius" />
    <edge source="jarmo" target="ilyam8" />
    <edge source="jarmo" target="Ferroin" />
    <edge source="jarmo" target="maneamarius" />
    <edge source="jarmo" target="solution-al" />
    <edge source="cvalentine99" target="ilyam8" />
    <edge source="cvalentine99" target="cpipilas" />
    <edge source="SteveBox0" target="ilyam8" />
    <edge source="SteveBox0" target="cpipilas" />
    <edge source="SteveBox0" target="Ferroin" />
    <edge source="SteveBox0" target="maneamarius" />
    <edge source="SteveBox0" target="vlvkobal" />
    <edge source="SteveBox0" target="stelfrag" />
    <edge source="cpipilas" target="ilyam8" />
    <edge source="cpipilas" target="anilskalyane" />
    <edge source="cpipilas" target="MatthewABrantley" />
    <edge source="cpipilas" target="underhood" />
    <edge source="cpipilas" target="gary-albano" />
    <edge source="cpipilas" target="hugovalente-pm" />
    <edge source="cpipilas" target="netdata-community-bot" />
    <edge source="cpipilas" target="MrZammler" />
    <edge source="cpipilas" target="DmitruMoth" />
    <edge source="cpipilas" target="Ferroin" />
    <edge source="cpipilas" target="PatTheMav" />
    <edge source="cpipilas" target="andrewm4894" />
    <edge source="cpipilas" target="tkatsoulas" />
    <edge source="cpipilas" target="William8Work" />
    <edge source="cpipilas" target="vickyingle01" />
    <edge source="cpipilas" target="cakrit" />
    <edge source="cpipilas" target="vlvkobal" />
    <edge source="cpipilas" target="PanosJee" />
    <edge source="cpipilas" target="vkuznecovas" />
    <edge source="cpipilas" target="maneamarius" />
    <edge source="cpipilas" target="timowevel1" />
    <edge source="cpipilas" target="xyzulu" />
    <edge source="cpipilas" target="stelfrag" />
    <edge source="cpipilas" target="Anasxrt" />
    <edge source="ghuntley" target="Ferroin" />
    <edge source="ghuntley" target="maneamarius" />
    <edge source="ewlikodjo" target="ilyam8" />
    <edge source="ewlikodjo" target="Ferroin" />
    <edge source="ewlikodjo" target="maneamarius" />
    <edge source="ewlikodjo" target="IslamAlam" />
    <edge source="ilyam8" target="thunko" />
    <edge source="ilyam8" target="surajnpn" />
    <edge source="ilyam8" target="MatthewABrantley" />
    <edge source="ilyam8" target="hx210" />
    <edge source="ilyam8" target="IDeletedSystem64" />
    <edge source="ilyam8" target="hugovalente-pm" />
    <edge source="ilyam8" target="MrZammler" />
    <edge source="ilyam8" target="DmitruMoth" />
    <edge source="ilyam8" target="Famku" />
    <edge source="ilyam8" target="lzclff" />
    <edge source="ilyam8" target="PatTheMav" />
    <edge source="ilyam8" target="andrewm4894" />
    <edge source="ilyam8" target="k0ste" />
    <edge source="ilyam8" target="tkatsoulas" />
    <edge source="ilyam8" target="drawks" />
    <edge source="ilyam8" target="maneamarius" />
    <edge source="ilyam8" target="renantea" />
    <edge source="ilyam8" target="IslamAlam" />
    <edge source="ilyam8" target="thiagoftsm" />
    <edge source="ilyam8" target="diizzyy" />
    <edge source="ilyam8" target="superusercode" />
    <edge source="ilyam8" target="mikehearn" />
    <edge source="ilyam8" target="gmta" />
    <edge source="ilyam8" target="jinetjose" />
    <edge source="ilyam8" target="odidev" />
    <edge source="ilyam8" target="callumgare" />
    <edge source="ilyam8" target="underhood" />
    <edge source="ilyam8" target="ghoekstra" />
    <edge source="ilyam8" target="ralphm" />
    <edge source="ilyam8" target="kryztoval" />
    <edge source="ilyam8" target="netdata-community-bot" />
    <edge source="ilyam8" target="tomeq82" />
    <edge source="ilyam8" target="ValorousSalmon" />
    <edge source="ilyam8" target="Ferroin" />
    <edge source="ilyam8" target="jrca025" />
    <edge source="ilyam8" target="RubenKelevra" />
    <edge source="ilyam8" target="vlvkobal" />
    <edge source="ilyam8" target="PanosJee" />
    <edge source="ilyam8" target="cakrit" />
    <edge source="ilyam8" target="Piroro-hs" />
    <edge source="ilyam8" target="crafty35a" />
    <edge source="ilyam8" target="solution-al" />
    <edge source="ilyam8" target="realEthanZou" />
    <edge source="ilyam8" target="luison" />
    <edge source="ilyam8" target="stelfrag" />
    <edge source="netdata-community-bot" target="Ferroin" />
    <edge source="netdata-community-bot" target="maneamarius" />
    <edge source="netdata-community-bot" target="tkatsoulas" />
    <edge source="netdata-community-bot" target="MrZammler" />
    <edge source="netdata-community-bot" target="vlvkobal" />
    <edge source="netdata-community-bot" target="Famku" />
    <edge source="netdata-community-bot" target="ghoekstra" />
    <edge source="netdata-community-bot" target="anilskalyane" />
    <edge source="netdata-community-bot" target="vickyingle01" />
    <edge source="netdata-community-bot" target="cakrit" />
    <edge source="netdata-community-bot" target="gary-albano" />
    <edge source="netdata-community-bot" target="renantea" />
    <edge source="netdata-community-bot" target="timowevel1" />
    <edge source="netdata-community-bot" target="xyzulu" />
    <edge source="netdata-community-bot" target="ktsaou" />
    <edge source="tomeq82" target="Ferroin" />
    <edge source="tomeq82" target="maneamarius" />
    <edge source="ValorousSalmon" target="Ferroin" />
    <edge source="ValorousSalmon" target="maneamarius" />
    <edge source="Ferroin" target="odidev" />
    <edge source="Ferroin" target="underhood" />
    <edge source="Ferroin" target="kryztoval" />
    <edge source="Ferroin" target="MrZammler" />
    <edge source="Ferroin" target="ktsaou" />
    <edge source="Ferroin" target="PatTheMav" />
    <edge source="Ferroin" target="tkatsoulas" />
    <edge source="Ferroin" target="William8Work" />
    <edge source="Ferroin" target="drawks" />
    <edge source="Ferroin" target="vlvkobal" />
    <edge source="Ferroin" target="maneamarius" />
    <edge source="Ferroin" target="Piroro-hs" />
    <edge source="Ferroin" target="renantea" />
    <edge source="Ferroin" target="IslamAlam" />
    <edge source="Ferroin" target="thiagoftsm" />
    <edge source="Ferroin" target="solution-al" />
    <edge source="Ferroin" target="superusercode" />
    <edge source="Ferroin" target="mikehearn" />
    <edge source="Ferroin" target="stelfrag" />
    <edge source="Ferroin" target="gmta" />
    <edge source="ktsaou" target="maneamarius" />
    <edge source="ktsaou" target="tkatsoulas" />
    <edge source="ktsaou" target="stelfrag" />
    <edge source="PatTheMav" target="mikehearn" />
    <edge source="PatTheMav" target="tkatsoulas" />
    <edge source="PatTheMav" target="maneamarius" />
    <edge source="tkatsoulas" target="maneamarius" />
    <edge source="vlvkobal" target="maneamarius" />
    <edge source="vlvkobal" target="MrZammler" />
    <edge source="vlvkobal" target="callumgare" />
    <edge source="vlvkobal" target="andrewm4894" />
    <edge source="vlvkobal" target="k0ste" />
    <edge source="vlvkobal" target="PanosJee" />
    <edge source="vlvkobal" target="ralphm" />
    <edge source="vlvkobal" target="renantea" />
    <edge source="vlvkobal" target="stelfrag" />
    <edge source="vlvkobal" target="gmta" />
    <edge source="maneamarius" target="mikehearn" />
    <edge source="maneamarius" target="Piroro-hs" />
    <edge source="maneamarius" target="renantea" />
    <edge source="maneamarius" target="IslamAlam" />
    <edge source="maneamarius" target="solution-al" />
    <edge source="maneamarius" target="stelfrag" />
    <edge source="stelfrag" target="MrZammler" />
    <edge source="stelfrag" target="cakrit" />
    <edge source="stelfrag" target="hugovalente-pm" />
    <edge source="MatthewABrantley" target="MrZammler" />
    <edge source="IDeletedSystem64" target="MrZammler" />
    <edge source="IDeletedSystem64" target="diizzyy" />
    <edge source="IDeletedSystem64" target="thiagoftsm" />
    <edge source="hugovalente-pm" target="MrZammler" />
    <edge source="hugovalente-pm" target="thiagoftsm" />
    <edge source="hugovalente-pm" target="cakrit" />
    <edge source="MrZammler" target="anilskalyane" />
    <edge source="MrZammler" target="callumgare" />
    <edge source="MrZammler" target="iredmail" />
    <edge source="MrZammler" target="gary-albano" />
    <edge source="MrZammler" target="jrca025" />
    <edge source="MrZammler" target="William8Work" />
    <edge source="MrZammler" target="vickyingle01" />
    <edge source="MrZammler" target="cakrit" />
    <edge source="MrZammler" target="vkuznecovas" />
    <edge source="MrZammler" target="timowevel1" />
    <edge source="MrZammler" target="thiagoftsm" />
    <edge source="MrZammler" target="diizzyy" />
    <edge source="MrZammler" target="xyzulu" />
    <edge source="MrZammler" target="Anasxrt" />
    <edge source="Famku" target="ghoekstra" />
    <edge source="lzclff" target="cakrit" />
    <edge source="lzclff" target="underhood" />
    <edge source="andrewm4894" target="PanosJee" />
    <edge source="drawks" target="thiagoftsm" />
    <edge source="thiagoftsm" target="diizzyy" />
    <edge source="superusercode" target="odidev" />
    <edge source="underhood" target="cakrit" />
    <edge source="cakrit" target="anilskalyane" />
    <edge source="cakrit" target="vickyingle01" />
    <edge source="cakrit" target="gary-albano" />
    <edge source="cakrit" target="timowevel1" />
    <edge source="cakrit" target="realEthanZou" />
    <edge source="cakrit" target="xyzulu" />
    <edge source="anilskalyane" target="vickyingle01" />
    <edge source="anilskalyane" target="xyzulu" />
    <edge source="anilskalyane" target="gary-albano" />
    <edge source="anilskalyane" target="timowevel1" />
    <edge source="gary-albano" target="vickyingle01" />
    <edge source="gary-albano" target="xyzulu" />
    <edge source="gary-albano" target="timowevel1" />
    <edge source="vickyingle01" target="xyzulu" />
    <edge source="vickyingle01" target="timowevel1" />
    <edge source="timowevel1" target="xyzulu" />
    <edge source="dragon2611" target="odynik" />
    <edge source="shyamvalsan" target="vkalintiris" />
    <edge source="vkalintiris" target="webdock-io" />
  </graph>
</graphml>
