<?xml version='1.0' encoding='utf-8'?>
<graphml xmlns="http://graphml.graphdrawing.org/xmlns" xmlns:xsi="http://www.w3.org/2001/XMLSchema-instance" xsi:schemaLocation="http://graphml.graphdrawing.org/xmlns http://graphml.graphdrawing.org/xmlns/1.0/graphml.xsd">
  <graph edgedefault="undirected">
    <node id="patrickvonplaten" />
    <node id="Narsil" />
    <node id="davidmezzetti" />
    <node id="djstrong" />
    <node id="Sonali234" />
    <node id="kventinel" />
    <node id="ydshieh" />
    <node id="gkarozis" />
    <node id="gante" />
    <node id="ishamnewsreels" />
    <node id="NamburiSrinath" />
    <node id="sgugger" />
    <node id="chujiezheng" />
    <node id="raghavanone" />
    <node id="ArthurZucker" />
    <node id="YiandLi" />
    <node id="BalazsFeherUK" />
    <node id="sanchit-gandhi" />
    <node id="NielsRogge" />
    <node id="amankhandelia" />
    <node id="elmadany" />
    <node id="CaffreyR" />
    <node id="pradeepdev-1995" />
    <node id="michaelbenayoun" />
    <node id="gidzr" />
    <node id="LysandreJik" />
    <node id="ddaspit" />
    <node id="amyeroberts" />
    <node id="FurkanGozukara" />
    <node id="avidale" />
    <node id="vince62s" />
    <node id="JohnnyRacer" />
    <node id="JeffreyWardman" />
    <node id="kurianbenoy-sentient" />
    <node id="GaetanBaert" />
    <node id="ariG23498" />
    <node id="nevakrien" />
    <node id="morrisalp" />
    <node id="chibeze01" />
    <node id="wildgeece96" />
    <node id="philschmid" />
    <node id="Zcchill" />
    <node id="Bearnardd" />
    <node id="BheemraoRodda" />
    <node id="quancore" />
    <node id="hcscctv" />
    <node id="rohit1998" />
    <node id="gmftbyGMFTBY" />
    <node id="chaodreaming" />
    <node id="ionutmodo" />
    <node id="MUZAMMILPERVAIZ" />
    <node id="xhluca" />
    <node id="SamuelCahyawijaya" />
    <node id="stefan-it" />
    <node id="martinez-zacharya" />
    <node id="sgunasekar" />
    <node id="carschno" />
    <node id="dmiller1-godaddy" />
    <node id="FrancescoTroiano" />
    <node id="IgorPidik" />
    <node id="yezhipeng2417" />
    <node id="cokuehuang" />
    <node id="mct-lrh" />
    <node id="IlyasMoutawwakil" />
    <node id="AndreasMadsen" />
    <node id="zzaebok" />
    <node id="hackpk" />
    <node id="leoleoasd" />
    <node id="muellerzr" />
    <node id="Lorenzobattistela" />
    <node id="yazdanbakhsh" />
    <node id="ahxchzt" />
    <node id="ra-MANUJ-an" />
    <node id="ArchontisKostis" />
    <node id="ayaka14732" />
    <node id="swap-10" />
    <node id="Abhiram4572" />
    <node id="stancld" />
    <node id="mht-sharma" />
    <node id="lewtun" />
    <node id="Xappuccino" />
    <node id="TrentBrick" />
    <node id="amrsharaf" />
    <node id="bugm" />
    <node id="fssh72" />
    <node id="pavibhai" />
    <node id="ccmaymay" />
    <node id="adit299" />
    <node id="piEsposito" />
    <node id="jegork" />
    <node id="Khixinhxan" />
    <node id="monk1337" />
    <node id="mohammad-sajeel" />
    <node id="Rocketknight1" />
    <node id="surya-narayanan" />
    <node id="devozs" />
    <node id="MichaleDong" />
    <node id="davidavdav" />
    <node id="LTEnjoy" />
    <node id="RockMiin" />
    <node id="tarokiritani" />
    <node id="calvingiles" />
    <node id="BakingBrains" />
    <node id="chenmoneygithub" />
    <node id="abhinav-kashyap-asus" />
    <node id="FlorinAndrei" />
    <node id="atyshka" />
    <node id="chris-aeviator" />
    <node id="Iron-man-0" />
    <node id="nsthorat" />
    <node id="shabha7092" />
    <node id="daspartho" />
    <node id="NYcleaner" />
    <node id="StefanHeng" />
    <node id="Yang-YiFan" />
    <node id="bk1n" />
    <node id="Amlalqhtani" />
    <node id="abnokubi" />
    <node id="urialon" />
    <node id="ZiyueWangUoB" />
    <node id="nayanukande" />
    <node id="andreabac3" />
    <node id="nyadla-sys" />
    <node id="uglyboxer" />
    <node id="zeynabyousefi" />
    <node id="sayakpaul" />
    <node id="asrimanth" />
    <node id="IMvision12" />
    <node id="venkat-natchi" />
    <node id="y3sar" />
    <node id="stevhliu" />
    <node id="RoyiRa" />
    <node id="divyam-prajapati" />
    <node id="ENate" />
    <node id="pbaner16" />
    <node id="conceptofmind" />
    <node id="raj-pandey55" />
    <node id="SarangShrivastava" />
    <node id="entropy2333" />
    <node id="MarkRich" />
    <node id="BenoitLeguay" />
    <node id="unitinguncle" />
    <node id="thibaultdouzon" />
    <node id="mnaylor5" />
    <node id="purnasai-cyient" />
    <node id="mohit-217" />
    <node id="lingjzhu" />
    <node id="Fritskee" />
    <node id="a-ozbek" />
    <node id="RobertHua96" />
    <node id="JuheonChu" />
    <node id="fxmarty" />
    <node id="rajveer43" />
    <node id="shivance" />
    <node id="Tylersuard" />
    <node id="avisinghal6" />
    <node id="muxitox" />
    <node id="lchustc" />
    <node id="WaterKnight1998" />
    <node id="satheeshkatipomu" />
    <node id="atturaioe" />
    <node id="astariul" />
    <node id="hollance" />
    <node id="BENSAFOUAN-Abdelhalim" />
    <node id="IvanSedykh" />
    <node id="ilnarkz" />
    <node id="AndreaSottana" />
    <node id="paulpaul91" />
    <node id="uahmad235" />
    <node id="moksh-enf" />
    <node id="pchr8" />
    <node id="gal0is" />
    <node id="layjain" />
    <node id="ilyalasy" />
    <node id="muhark" />
    <node id="efima-ai" />
    <node id="theRealMachineWhisperer" />
    <node id="mbrotos" />
    <node id="johko" />
    <node id="pretbc" />
    <node id="fcakyon" />
    <node id="sywangyi" />
    <edge source="patrickvonplaten" target="Narsil" />
    <edge source="patrickvonplaten" target="davidmezzetti" />
    <edge source="patrickvonplaten" target="djstrong" />
    <edge source="patrickvonplaten" target="Sonali234" />
    <edge source="patrickvonplaten" target="kventinel" />
    <edge source="patrickvonplaten" target="ydshieh" />
    <edge source="patrickvonplaten" target="gkarozis" />
    <edge source="patrickvonplaten" target="gante" />
    <edge source="patrickvonplaten" target="ishamnewsreels" />
    <edge source="patrickvonplaten" target="NamburiSrinath" />
    <edge source="patrickvonplaten" target="sgugger" />
    <edge source="patrickvonplaten" target="chujiezheng" />
    <edge source="patrickvonplaten" target="raghavanone" />
    <edge source="patrickvonplaten" target="ArthurZucker" />
    <edge source="patrickvonplaten" target="YiandLi" />
    <edge source="patrickvonplaten" target="BalazsFeherUK" />
    <edge source="patrickvonplaten" target="sanchit-gandhi" />
    <edge source="patrickvonplaten" target="NielsRogge" />
    <edge source="patrickvonplaten" target="amankhandelia" />
    <edge source="patrickvonplaten" target="elmadany" />
    <edge source="patrickvonplaten" target="CaffreyR" />
    <edge source="Narsil" target="ArthurZucker" />
    <edge source="Narsil" target="morrisalp" />
    <edge source="Narsil" target="chibeze01" />
    <edge source="Narsil" target="davidmezzetti" />
    <edge source="Narsil" target="djstrong" />
    <edge source="Narsil" target="wildgeece96" />
    <edge source="Narsil" target="ydshieh" />
    <edge source="Narsil" target="philschmid" />
    <edge source="Narsil" target="Zcchill" />
    <edge source="Narsil" target="gante" />
    <edge source="Narsil" target="Bearnardd" />
    <edge source="Narsil" target="BheemraoRodda" />
    <edge source="Narsil" target="quancore" />
    <edge source="Narsil" target="sgugger" />
    <edge source="Narsil" target="hcscctv" />
    <edge source="Narsil" target="rohit1998" />
    <edge source="Narsil" target="gmftbyGMFTBY" />
    <edge source="Narsil" target="chaodreaming" />
    <edge source="davidmezzetti" target="gante" />
    <edge source="davidmezzetti" target="Bearnardd" />
    <edge source="davidmezzetti" target="sgugger" />
    <edge source="djstrong" target="ArthurZucker" />
    <edge source="djstrong" target="sgugger" />
    <edge source="djstrong" target="ydshieh" />
    <edge source="Sonali234" target="ArthurZucker" />
    <edge source="Sonali234" target="kventinel" />
    <edge source="Sonali234" target="gkarozis" />
    <edge source="kventinel" target="ArthurZucker" />
    <edge source="kventinel" target="NielsRogge" />
    <edge source="kventinel" target="gkarozis" />
    <edge source="kventinel" target="Fritskee" />
    <edge source="kventinel" target="entropy2333" />
    <edge source="kventinel" target="mht-sharma" />
    <edge source="ydshieh" target="ArthurZucker" />
    <edge source="ydshieh" target="sgugger" />
    <edge source="ydshieh" target="muxitox" />
    <edge source="ydshieh" target="lchustc" />
    <edge source="gkarozis" target="ArthurZucker" />
    <edge source="gante" target="CaffreyR" />
    <edge source="gante" target="sgugger" />
    <edge source="gante" target="morrisalp" />
    <edge source="gante" target="LysandreJik" />
    <edge source="gante" target="FurkanGozukara" />
    <edge source="gante" target="lewtun" />
    <edge source="gante" target="ZiyueWangUoB" />
    <edge source="gante" target="nayanukande" />
    <edge source="gante" target="andreabac3" />
    <edge source="gante" target="nyadla-sys" />
    <edge source="gante" target="amrsharaf" />
    <edge source="gante" target="zzaebok" />
    <edge source="gante" target="uglyboxer" />
    <edge source="gante" target="abhinav-kashyap-asus" />
    <edge source="gante" target="ccmaymay" />
    <edge source="gante" target="zeynabyousefi" />
    <edge source="gante" target="sanchit-gandhi" />
    <edge source="gante" target="NielsRogge" />
    <edge source="gante" target="piEsposito" />
    <edge source="gante" target="atyshka" />
    <edge source="gante" target="sayakpaul" />
    <edge source="ishamnewsreels" target="sanchit-gandhi" />
    <edge source="NamburiSrinath" target="pradeepdev-1995" />
    <edge source="NamburiSrinath" target="michaelbenayoun" />
    <edge source="NamburiSrinath" target="sgugger" />
    <edge source="NamburiSrinath" target="ArthurZucker" />
    <edge source="NamburiSrinath" target="CaffreyR" />
    <edge source="sgugger" target="ArthurZucker" />
    <edge source="sgugger" target="CaffreyR" />
    <edge source="sgugger" target="ionutmodo" />
    <edge source="sgugger" target="morrisalp" />
    <edge source="sgugger" target="MUZAMMILPERVAIZ" />
    <edge source="sgugger" target="chibeze01" />
    <edge source="sgugger" target="xhluca" />
    <edge source="sgugger" target="SamuelCahyawijaya" />
    <edge source="sgugger" target="stefan-it" />
    <edge source="sgugger" target="martinez-zacharya" />
    <edge source="sgugger" target="sgunasekar" />
    <edge source="sgugger" target="carschno" />
    <edge source="sgugger" target="dmiller1-godaddy" />
    <edge source="sgugger" target="FrancescoTroiano" />
    <edge source="sgugger" target="JohnnyRacer" />
    <edge source="sgugger" target="IgorPidik" />
    <edge source="sgugger" target="Zcchill" />
    <edge source="sgugger" target="yezhipeng2417" />
    <edge source="sgugger" target="cokuehuang" />
    <edge source="sgugger" target="mct-lrh" />
    <edge source="sgugger" target="IlyasMoutawwakil" />
    <edge source="sgugger" target="AndreasMadsen" />
    <edge source="sgugger" target="kurianbenoy-sentient" />
    <edge source="sgugger" target="zzaebok" />
    <edge source="sgugger" target="hackpk" />
    <edge source="sgugger" target="leoleoasd" />
    <edge source="sgugger" target="rohit1998" />
    <edge source="sgugger" target="muellerzr" />
    <edge source="sgugger" target="Lorenzobattistela" />
    <edge source="sgugger" target="yazdanbakhsh" />
    <edge source="sgugger" target="NielsRogge" />
    <edge source="sgugger" target="ahxchzt" />
    <edge source="sgugger" target="ra-MANUJ-an" />
    <edge source="sgugger" target="ArchontisKostis" />
    <edge source="sgugger" target="ayaka14732" />
    <edge source="sgugger" target="swap-10" />
    <edge source="sgugger" target="Abhiram4572" />
    <edge source="sgugger" target="stancld" />
    <edge source="sgugger" target="amyeroberts" />
    <edge source="sgugger" target="mht-sharma" />
    <edge source="sgugger" target="lewtun" />
    <edge source="sgugger" target="Xappuccino" />
    <edge source="sgugger" target="TrentBrick" />
    <edge source="sgugger" target="amrsharaf" />
    <edge source="sgugger" target="bugm" />
    <edge source="sgugger" target="fssh72" />
    <edge source="sgugger" target="pavibhai" />
    <edge source="sgugger" target="ccmaymay" />
    <edge source="sgugger" target="adit299" />
    <edge source="sgugger" target="michaelbenayoun" />
    <edge source="sgugger" target="piEsposito" />
    <edge source="sgugger" target="jegork" />
    <edge source="sgugger" target="Khixinhxan" />
    <edge source="sgugger" target="monk1337" />
    <edge source="sgugger" target="mohammad-sajeel" />
    <edge source="sgugger" target="Rocketknight1" />
    <edge source="sgugger" target="surya-narayanan" />
    <edge source="sgugger" target="devozs" />
    <edge source="sgugger" target="MichaleDong" />
    <edge source="sgugger" target="davidavdav" />
    <edge source="sgugger" target="FurkanGozukara" />
    <edge source="sgugger" target="LTEnjoy" />
    <edge source="sgugger" target="RockMiin" />
    <edge source="sgugger" target="tarokiritani" />
    <edge source="sgugger" target="calvingiles" />
    <edge source="sgugger" target="JeffreyWardman" />
    <edge source="sgugger" target="BakingBrains" />
    <edge source="sgugger" target="chujiezheng" />
    <edge source="sgugger" target="chenmoneygithub" />
    <edge source="sgugger" target="raghavanone" />
    <edge source="sgugger" target="abhinav-kashyap-asus" />
    <edge source="sgugger" target="ariG23498" />
    <edge source="sgugger" target="FlorinAndrei" />
    <edge source="sgugger" target="atyshka" />
    <edge source="sgugger" target="chaodreaming" />
    <edge source="sgugger" target="pradeepdev-1995" />
    <edge source="sgugger" target="chris-aeviator" />
    <edge source="sgugger" target="LysandreJik" />
    <edge source="sgugger" target="Iron-man-0" />
    <edge source="sgugger" target="nsthorat" />
    <edge source="sgugger" target="shabha7092" />
    <edge source="sgugger" target="daspartho" />
    <edge source="sgugger" target="NYcleaner" />
    <edge source="sgugger" target="StefanHeng" />
    <edge source="sgugger" target="Bearnardd" />
    <edge source="sgugger" target="Yang-YiFan" />
    <edge source="sgugger" target="bk1n" />
    <edge source="sgugger" target="Amlalqhtani" />
    <edge source="sgugger" target="abnokubi" />
    <edge source="sgugger" target="sanchit-gandhi" />
    <edge source="sgugger" target="urialon" />
    <edge source="chujiezheng" target="ArthurZucker" />
    <edge source="chujiezheng" target="NielsRogge" />
    <edge source="chujiezheng" target="BalazsFeherUK" />
    <edge source="raghavanone" target="ArthurZucker" />
    <edge source="raghavanone" target="atturaioe" />
    <edge source="raghavanone" target="astariul" />
    <edge source="raghavanone" target="ariG23498" />
    <edge source="raghavanone" target="LysandreJik" />
    <edge source="raghavanone" target="hollance" />
    <edge source="raghavanone" target="amyeroberts" />
    <edge source="ArthurZucker" target="gidzr" />
    <edge source="ArthurZucker" target="LysandreJik" />
    <edge source="ArthurZucker" target="ddaspit" />
    <edge source="ArthurZucker" target="amyeroberts" />
    <edge source="ArthurZucker" target="FurkanGozukara" />
    <edge source="ArthurZucker" target="avidale" />
    <edge source="ArthurZucker" target="vince62s" />
    <edge source="ArthurZucker" target="JohnnyRacer" />
    <edge source="ArthurZucker" target="JeffreyWardman" />
    <edge source="ArthurZucker" target="kurianbenoy-sentient" />
    <edge source="ArthurZucker" target="GaetanBaert" />
    <edge source="ArthurZucker" target="BalazsFeherUK" />
    <edge source="ArthurZucker" target="sanchit-gandhi" />
    <edge source="ArthurZucker" target="NielsRogge" />
    <edge source="ArthurZucker" target="ariG23498" />
    <edge source="ArthurZucker" target="nevakrien" />
    <edge source="ArthurZucker" target="CaffreyR" />
    <edge source="YiandLi" target="elmadany" />
    <edge source="BalazsFeherUK" target="NielsRogge" />
    <edge source="sanchit-gandhi" target="sayakpaul" />
    <edge source="sanchit-gandhi" target="nyadla-sys" />
    <edge source="sanchit-gandhi" target="zeynabyousefi" />
    <edge source="sanchit-gandhi" target="JeffreyWardman" />
    <edge source="sanchit-gandhi" target="kurianbenoy-sentient" />
    <edge source="sanchit-gandhi" target="amankhandelia" />
    <edge source="NielsRogge" target="uglyboxer" />
    <edge source="NielsRogge" target="y3sar" />
    <edge source="NielsRogge" target="stevhliu" />
    <edge source="NielsRogge" target="RoyiRa" />
    <edge source="NielsRogge" target="MUZAMMILPERVAIZ" />
    <edge source="NielsRogge" target="divyam-prajapati" />
    <edge source="NielsRogge" target="SamuelCahyawijaya" />
    <edge source="NielsRogge" target="ENate" />
    <edge source="NielsRogge" target="pbaner16" />
    <edge source="NielsRogge" target="conceptofmind" />
    <edge source="NielsRogge" target="tarokiritani" />
    <edge source="NielsRogge" target="raj-pandey55" />
    <edge source="NielsRogge" target="SarangShrivastava" />
    <edge source="NielsRogge" target="hackpk" />
    <edge source="NielsRogge" target="GaetanBaert" />
    <edge source="NielsRogge" target="Lorenzobattistela" />
    <edge source="NielsRogge" target="entropy2333" />
    <edge source="NielsRogge" target="MarkRich" />
    <edge source="NielsRogge" target="BenoitLeguay" />
    <edge source="NielsRogge" target="unitinguncle" />
    <edge source="NielsRogge" target="LysandreJik" />
    <edge source="NielsRogge" target="thibaultdouzon" />
    <edge source="NielsRogge" target="mnaylor5" />
    <edge source="NielsRogge" target="purnasai-cyient" />
    <edge source="NielsRogge" target="mht-sharma" />
    <edge source="NielsRogge" target="daspartho" />
    <edge source="NielsRogge" target="lewtun" />
    <edge source="NielsRogge" target="nayanukande" />
    <edge source="NielsRogge" target="mohit-217" />
    <edge source="NielsRogge" target="lingjzhu" />
    <edge source="NielsRogge" target="Fritskee" />
    <edge source="NielsRogge" target="a-ozbek" />
    <edge source="NielsRogge" target="RobertHua96" />
    <edge source="NielsRogge" target="JuheonChu" />
    <edge source="NielsRogge" target="adit299" />
    <edge source="NielsRogge" target="fxmarty" />
    <edge source="NielsRogge" target="rajveer43" />
    <edge source="NielsRogge" target="sayakpaul" />
    <edge source="NielsRogge" target="shivance" />
    <edge source="NielsRogge" target="Tylersuard" />
    <edge source="NielsRogge" target="avisinghal6" />
    <edge source="CaffreyR" target="LysandreJik" />
    <edge source="pradeepdev-1995" target="michaelbenayoun" />
    <edge source="gidzr" target="ddaspit" />
    <edge source="gidzr" target="avidale" />
    <edge source="gidzr" target="vince62s" />
    <edge source="gidzr" target="nevakrien" />
    <edge source="LysandreJik" target="nyadla-sys" />
    <edge source="LysandreJik" target="atturaioe" />
    <edge source="LysandreJik" target="ilnarkz" />
    <edge source="LysandreJik" target="astariul" />
    <edge source="LysandreJik" target="Rocketknight1" />
    <edge source="LysandreJik" target="AndreaSottana" />
    <edge source="LysandreJik" target="amyeroberts" />
    <edge source="LysandreJik" target="purnasai-cyient" />
    <edge source="LysandreJik" target="zzaebok" />
    <edge source="LysandreJik" target="abhinav-kashyap-asus" />
    <edge source="LysandreJik" target="ariG23498" />
    <edge source="LysandreJik" target="hollance" />
    <edge source="LysandreJik" target="BENSAFOUAN-Abdelhalim" />
    <edge source="LysandreJik" target="atyshka" />
    <edge source="ddaspit" target="nevakrien" />
    <edge source="ddaspit" target="avidale" />
    <edge source="ddaspit" target="vince62s" />
    <edge source="amyeroberts" target="muellerzr" />
    <edge source="amyeroberts" target="ariG23498" />
    <edge source="avidale" target="nevakrien" />
    <edge source="avidale" target="vince62s" />
    <edge source="vince62s" target="nevakrien" />
    <edge source="JeffreyWardman" target="kurianbenoy-sentient" />
    <edge source="chibeze01" target="rohit1998" />
    <edge source="wildgeece96" target="philschmid" />
    <edge source="Zcchill" target="gmftbyGMFTBY" />
    <edge source="Zcchill" target="BheemraoRodda" />
    <edge source="Zcchill" target="paulpaul91" />
    <edge source="BheemraoRodda" target="gmftbyGMFTBY" />
    <edge source="ionutmodo" target="TrentBrick" />
    <edge source="SamuelCahyawijaya" target="adit299" />
    <edge source="SamuelCahyawijaya" target="daspartho" />
    <edge source="SamuelCahyawijaya" target="hackpk" />
    <edge source="SamuelCahyawijaya" target="Lorenzobattistela" />
    <edge source="stefan-it" target="AndreasMadsen" />
    <edge source="mct-lrh" target="monk1337" />
    <edge source="mct-lrh" target="surya-narayanan" />
    <edge source="mct-lrh" target="Abhiram4572" />
    <edge source="IlyasMoutawwakil" target="lewtun" />
    <edge source="IlyasMoutawwakil" target="mht-sharma" />
    <edge source="IlyasMoutawwakil" target="mohammad-sajeel" />
    <edge source="zzaebok" target="atyshka" />
    <edge source="zzaebok" target="abhinav-kashyap-asus" />
    <edge source="hackpk" target="adit299" />
    <edge source="hackpk" target="daspartho" />
    <edge source="hackpk" target="Lorenzobattistela" />
    <edge source="leoleoasd" target="pavibhai" />
    <edge source="leoleoasd" target="NYcleaner" />
    <edge source="leoleoasd" target="chris-aeviator" />
    <edge source="Lorenzobattistela" target="adit299" />
    <edge source="Lorenzobattistela" target="daspartho" />
    <edge source="swap-10" target="Rocketknight1" />
    <edge source="Abhiram4572" target="monk1337" />
    <edge source="Abhiram4572" target="surya-narayanan" />
    <edge source="mht-sharma" target="lewtun" />
    <edge source="mht-sharma" target="Fritskee" />
    <edge source="mht-sharma" target="mohammad-sajeel" />
    <edge source="mht-sharma" target="BakingBrains" />
    <edge source="mht-sharma" target="WaterKnight1998" />
    <edge source="mht-sharma" target="satheeshkatipomu" />
    <edge source="mht-sharma" target="entropy2333" />
    <edge source="lewtun" target="BenoitLeguay" />
    <edge source="lewtun" target="mohammad-sajeel" />
    <edge source="lewtun" target="BakingBrains" />
    <edge source="lewtun" target="WaterKnight1998" />
    <edge source="lewtun" target="abnokubi" />
    <edge source="lewtun" target="satheeshkatipomu" />
    <edge source="lewtun" target="fxmarty" />
    <edge source="lewtun" target="ZiyueWangUoB" />
    <edge source="pavibhai" target="chris-aeviator" />
    <edge source="pavibhai" target="NYcleaner" />
    <edge source="adit299" target="daspartho" />
    <edge source="piEsposito" target="calvingiles" />
    <edge source="piEsposito" target="Rocketknight1" />
    <edge source="piEsposito" target="chenmoneygithub" />
    <edge source="Khixinhxan" target="shabha7092" />
    <edge source="Khixinhxan" target="Amlalqhtani" />
    <edge source="monk1337" target="surya-narayanan" />
    <edge source="Rocketknight1" target="nyadla-sys" />
    <edge source="Rocketknight1" target="calvingiles" />
    <edge source="Rocketknight1" target="BENSAFOUAN-Abdelhalim" />
    <edge source="Rocketknight1" target="chenmoneygithub" />
    <edge source="calvingiles" target="chenmoneygithub" />
    <edge source="BakingBrains" target="satheeshkatipomu" />
    <edge source="BakingBrains" target="WaterKnight1998" />
    <edge source="abhinav-kashyap-asus" target="atyshka" />
    <edge source="chris-aeviator" target="NYcleaner" />
    <edge source="shabha7092" target="Amlalqhtani" />
    <edge source="nayanukande" target="uglyboxer" />
    <edge source="nyadla-sys" target="sayakpaul" />
    <edge source="nyadla-sys" target="zeynabyousefi" />
    <edge source="nyadla-sys" target="BENSAFOUAN-Abdelhalim" />
    <edge source="zeynabyousefi" target="sayakpaul" />
    <edge source="sayakpaul" target="y3sar" />
    <edge source="sayakpaul" target="stevhliu" />
    <edge source="sayakpaul" target="raj-pandey55" />
    <edge source="sayakpaul" target="unitinguncle" />
    <edge source="sayakpaul" target="SarangShrivastava" />
    <edge source="sayakpaul" target="divyam-prajapati" />
    <edge source="sayakpaul" target="rajveer43" />
    <edge source="sayakpaul" target="ENate" />
    <edge source="sayakpaul" target="avisinghal6" />
    <edge source="asrimanth" target="IMvision12" />
    <edge source="asrimanth" target="venkat-natchi" />
    <edge source="IMvision12" target="venkat-natchi" />
    <edge source="y3sar" target="ENate" />
    <edge source="y3sar" target="SarangShrivastava" />
    <edge source="y3sar" target="stevhliu" />
    <edge source="y3sar" target="raj-pandey55" />
    <edge source="y3sar" target="unitinguncle" />
    <edge source="y3sar" target="divyam-prajapati" />
    <edge source="y3sar" target="rajveer43" />
    <edge source="y3sar" target="avisinghal6" />
    <edge source="stevhliu" target="ENate" />
    <edge source="stevhliu" target="SarangShrivastava" />
    <edge source="stevhliu" target="unitinguncle" />
    <edge source="stevhliu" target="raj-pandey55" />
    <edge source="stevhliu" target="divyam-prajapati" />
    <edge source="stevhliu" target="rajveer43" />
    <edge source="stevhliu" target="avisinghal6" />
    <edge source="RoyiRa" target="a-ozbek" />
    <edge source="RoyiRa" target="pbaner16" />
    <edge source="RoyiRa" target="thibaultdouzon" />
    <edge source="RoyiRa" target="JuheonChu" />
    <edge source="divyam-prajapati" target="ENate" />
    <edge source="divyam-prajapati" target="SarangShrivastava" />
    <edge source="divyam-prajapati" target="unitinguncle" />
    <edge source="divyam-prajapati" target="raj-pandey55" />
    <edge source="divyam-prajapati" target="rajveer43" />
    <edge source="divyam-prajapati" target="avisinghal6" />
    <edge source="ENate" target="raj-pandey55" />
    <edge source="ENate" target="unitinguncle" />
    <edge source="ENate" target="SarangShrivastava" />
    <edge source="ENate" target="rajveer43" />
    <edge source="ENate" target="avisinghal6" />
    <edge source="pbaner16" target="a-ozbek" />
    <edge source="pbaner16" target="JuheonChu" />
    <edge source="pbaner16" target="thibaultdouzon" />
    <edge source="raj-pandey55" target="SarangShrivastava" />
    <edge source="raj-pandey55" target="unitinguncle" />
    <edge source="raj-pandey55" target="rajveer43" />
    <edge source="raj-pandey55" target="avisinghal6" />
    <edge source="SarangShrivastava" target="unitinguncle" />
    <edge source="SarangShrivastava" target="rajveer43" />
    <edge source="SarangShrivastava" target="avisinghal6" />
    <edge source="entropy2333" target="Fritskee" />
    <edge source="MarkRich" target="mnaylor5" />
    <edge source="MarkRich" target="Tylersuard" />
    <edge source="MarkRich" target="lingjzhu" />
    <edge source="BenoitLeguay" target="fxmarty" />
    <edge source="unitinguncle" target="rajveer43" />
    <edge source="unitinguncle" target="avisinghal6" />
    <edge source="thibaultdouzon" target="a-ozbek" />
    <edge source="thibaultdouzon" target="JuheonChu" />
    <edge source="mnaylor5" target="lingjzhu" />
    <edge source="mnaylor5" target="Tylersuard" />
    <edge source="lingjzhu" target="Tylersuard" />
    <edge source="a-ozbek" target="JuheonChu" />
    <edge source="rajveer43" target="avisinghal6" />
    <edge source="WaterKnight1998" target="satheeshkatipomu" />
    <edge source="atturaioe" target="hollance" />
    <edge source="atturaioe" target="astariul" />
    <edge source="astariul" target="hollance" />
    <edge source="ilnarkz" target="AndreaSottana" />
    <edge source="uahmad235" target="moksh-enf" />
    <edge source="gal0is" target="layjain" />
    <edge source="gal0is" target="ilyalasy" />
    <edge source="gal0is" target="muhark" />
    <edge source="gal0is" target="efima-ai" />
    <edge source="gal0is" target="theRealMachineWhisperer" />
    <edge source="gal0is" target="mbrotos" />
    <edge source="layjain" target="ilyalasy" />
    <edge source="layjain" target="muhark" />
    <edge source="layjain" target="efima-ai" />
    <edge source="layjain" target="theRealMachineWhisperer" />
    <edge source="layjain" target="mbrotos" />
    <edge source="ilyalasy" target="muhark" />
    <edge source="ilyalasy" target="efima-ai" />
    <edge source="ilyalasy" target="theRealMachineWhisperer" />
    <edge source="ilyalasy" target="mbrotos" />
    <edge source="muhark" target="efima-ai" />
    <edge source="muhark" target="theRealMachineWhisperer" />
    <edge source="muhark" target="mbrotos" />
    <edge source="efima-ai" target="mbrotos" />
    <edge source="efima-ai" target="theRealMachineWhisperer" />
    <edge source="theRealMachineWhisperer" target="mbrotos" />
    <edge source="johko" target="pretbc" />
    <edge source="johko" target="fcakyon" />
    <edge source="pretbc" target="fcakyon" />
  </graph>
</graphml>
